bdx/__init__.py
bdx/auth.py
bdx/buildings.py
bdx/common.py
bdx/components.py
bdx/core.py
bdx/hierarchy.py
bdx/sessions.py
bdx/trending.py
bdx/types.py
bdxpy-1.0.2.dist-info/LICENSE
bdxpy-1.0.2.dist-info/METADATA
bdxpy-1.0.2.dist-info/WHEEL
bdxpy-1.0.2.dist-info/top_level.txt
bdxpy-1.0.2.dist-info/RECORD
