Metadata-Version: 2.2
Name: bdxpy
Version: 1.0.2
Summary: A client library for interfacing with the BDX platform.
Home-page: https://buildinglogix.github.io/BDXpy/
Author: BuildingLogiX
Author-email: Development.Request@buildinglogix.net
License: Proprietary
Classifier: Programming Language :: Python :: 3
Classifier: License :: Other/Proprietary License
Classifier: Operating System :: OS Independent
Requires-Python: >=3.12
License-File: LICENSE
Requires-Dist: PyNaCl>=1.5.0
Requires-Dist: requests>=2.32.3
Requires-Dist: urllib3>=2.3.0
Requires-Dist: dacite>=1.9.0
Requires-Dist: pandas>=2.2.3
